viiv/__init__.py
viiv/__main__.py
viiv/builtin_themes.py
viiv/conf/config.json
viiv/conf/nvim-themes.json
viiv/converter.py
viiv/generators/__init__.py
viiv/generators/nvim.py
viiv/generators/vscode.py
viiv/utils.py
viiv/viiv.py
viiv-1.0.7.dist-info/METADATA
viiv-1.0.7.dist-info/WHEEL
viiv-1.0.7.dist-info/licenses/LICENSE
viiv-1.0.7.dist-info/RECORD
