Metadata-Version: 2.4
Name: viiv
Version: 1.0.7
Summary: A python library to create vscode themes.
License: MIT
License-File: LICENSE
Author: Bruce Wen
Author-email: wenijinew@gmail.com
Requires-Python: >=3.11,<4.0
Classifier: License :: OSI Approved :: MIT License
Classifier: Programming Language :: Python :: 3
Classifier: Programming Language :: Python :: 3.11
Classifier: Programming Language :: Python :: 3.12
Classifier: Programming Language :: Python :: 3.13
Classifier: Programming Language :: Python :: 3.14
Requires-Dist: build (>=1.2.2,<2.0.0)
Requires-Dist: dotenv (>=0.9.9,<0.10.0)
Requires-Dist: extcolors (>=1.0.0,<2.0.0)
Requires-Dist: loguru (>=0.7.2,<0.8.0)
Requires-Dist: numpy (>=2.1.1,<3.0.0)
Requires-Dist: peelee (>=0.2.48,<0.3.0)
Requires-Dist: pillow (>=10.3,<13.0)
Requires-Dist: pytest (>=8.3.3,<10.0.0)
